textractor/__init__.py
textractor/exceptions.py
textractor/textractor.py
textractor/cli/__init__.py
textractor/cli/cli.py
textractor/data/__init__.py
textractor/data/constants.py
textractor/data/html_linearization_config.py
textractor/data/markdown_linearization_config.py
textractor/data/text_linearization_config.py
textractor/entities/__init__.py
textractor/entities/bbox.py
textractor/entities/document.py
textractor/entities/document_entity.py
textractor/entities/expense_document.py
textractor/entities/expense_field.py
textractor/entities/identity_document.py
textractor/entities/identity_field.py
textractor/entities/key_value.py
textractor/entities/layout.py
textractor/entities/lazy_document.py
textractor/entities/line.py
textractor/entities/linearizable.py
textractor/entities/page.py
textractor/entities/page_layout.py
textractor/entities/query.py
textractor/entities/query_result.py
textractor/entities/selection_element.py
textractor/entities/signature.py
textractor/entities/table.py
textractor/entities/table_cell.py
textractor/entities/table_footer.py
textractor/entities/table_title.py
textractor/entities/value.py
textractor/entities/word.py
textractor/parsers/__init__.py
textractor/parsers/response_parser.py
textractor/utils/__init__.py
textractor/utils/geometry_util.py
textractor/utils/html_utils.py
textractor/utils/legacy_utils.py
textractor/utils/pdf_utils.py
textractor/utils/results_utils.py
textractor/utils/s3_utils.py
textractor/utils/search_utils.py
textractor/utils/text_utils.py
textractor/visualizers/__init__.py
textractor/visualizers/arial.ttf
textractor/visualizers/entitylist.py
amazon_textract_textractor-1.9.2.dist-info/LICENSE
amazon_textract_textractor-1.9.2.dist-info/METADATA
amazon_textract_textractor-1.9.2.dist-info/NOTICE
amazon_textract_textractor-1.9.2.dist-info/WHEEL
amazon_textract_textractor-1.9.2.dist-info/entry_points.txt
amazon_textract_textractor-1.9.2.dist-info/top_level.txt
amazon_textract_textractor-1.9.2.dist-info/RECORD
