Metadata-Version: 2.1
Name: amazon-textract-textractor
Version: 1.9.2
Summary: A package to use AWS Textract services.
Home-page: https://github.com/aws-samples/amazon-textract-textractor
License: Apache 2.0
Keywords: amazon textract aws ocr document
Classifier: Programming Language :: Python :: 3
Classifier: Programming Language :: Python :: 3.9
Classifier: Programming Language :: Python :: 3.10
Classifier: Programming Language :: Python :: 3.11
Classifier: Programming Language :: Python :: 3.12
License-File: LICENSE
License-File: NOTICE
Requires-Dist: Pillow
Requires-Dist: XlsxWriter <4,>=3.0
Requires-Dist: amazon-textract-caller <1,>=0.2.4
Requires-Dist: editdistance <0.9,>=0.6.2
Requires-Dist: tabulate <0.10,>=0.9
Provides-Extra: dev
Requires-Dist: jupyterlab ; extra == 'dev'
Requires-Dist: lxml ; extra == 'dev'
Requires-Dist: pandas ; extra == 'dev'
Requires-Dist: pdf2image <1.17,>=1.16 ; extra == 'dev'
Requires-Dist: pytest ; extra == 'dev'
Requires-Dist: sentence-transformers <2.3,>=2.2 ; extra == 'dev'
Requires-Dist: sphinx-rtd-theme <1.1,>=1.0 ; extra == 'dev'
Provides-Extra: docs
Requires-Dist: Sphinx <5.2,>=5.1 ; extra == 'docs'
Requires-Dist: jupyterlab ; extra == 'docs'
Requires-Dist: nbsphinx <0.9,>=0.8 ; extra == 'docs'
Requires-Dist: pandas ; extra == 'docs'
Requires-Dist: pdf2image <1.17,>=1.16 ; extra == 'docs'
Requires-Dist: pytest ; extra == 'docs'
Requires-Dist: sphinx-argparse >=0.5.1 ; extra == 'docs'
Requires-Dist: sphinx-rtd-theme <3.0,>=2.0 ; extra == 'docs'
Requires-Dist: sphinxcontrib-applehelp <1.1,>=1.0 ; extra == 'docs'
Requires-Dist: sphinxcontrib-devhelp <1.1,>=1.0 ; extra == 'docs'
Requires-Dist: sphinxcontrib-htmlhelp <2.1,>=2.0 ; extra == 'docs'
Requires-Dist: sphinxcontrib-jsmath <1.1,>=1.0 ; extra == 'docs'
Requires-Dist: sphinxcontrib-qthelp <1.1,>=1.0 ; extra == 'docs'
Requires-Dist: sphinxcontrib-serializinghtml <1.2,>=1.1 ; extra == 'docs'
Provides-Extra: pandas
Requires-Dist: pandas ; extra == 'pandas'
Provides-Extra: pdf
Requires-Dist: pdf2image <1.17,>=1.16 ; extra == 'pdf'
Provides-Extra: pdfium
Requires-Dist: pypdfium2 ; extra == 'pdfium'
Provides-Extra: torch
Requires-Dist: sentence-transformers <2.3,>=2.2 ; extra == 'torch'
